examples/example_usage.py
openassetpricing/__init__.py
openassetpricing/gdrive_parse.py
openassetpricing/openap_download.py
openassetpricing/urls.py
tests/test_example.py
tests/test_functions.py
tests/test_gdrive_parse.py
tests/urls.py
openassetpricing-0.0.2.dist-info/METADATA
openassetpricing-0.0.2.dist-info/WHEEL
openassetpricing-0.0.2.dist-info/top_level.txt
openassetpricing-0.0.2.dist-info/RECORD
