Metadata-Version: 2.4
Name: openassetpricing
Version: 0.0.2
Summary: Open asset pricing package with example dependencies
Author: Peng Li, Andrew Chen, Tom Zimmermann
Author-email: Peng Li <pl750@bath.ac.uk>, Andrew Chen <andrew.y.chen@frb.gov>, Tom Zimmermann <tom.zimmermann@uni-koeln.de>
License: GPLv2
Requires-Python: >=3.8
Requires-Dist: polars
Requires-Dist: pandas
Requires-Dist: requests
Requires-Dist: tabulate
Requires-Dist: wrds
Requires-Dist: pyarrow
Requires-Dist: beautifulsoup4
Provides-Extra: examples
Requires-Dist: matplotlib; extra == "examples"
Requires-Dist: numpy; extra == "examples"
Requires-Dist: scikit-learn; extra == "examples"
Requires-Dist: seaborn; extra == "examples"
Requires-Dist: statsmodels; extra == "examples"
Dynamic: author
